django_hyperscript/__init__.py
django_hyperscript/serializer.py
django_hyperscript/templatetags/__init__.py
django_hyperscript/templatetags/hyperscript.py
django_hyperscript-1.5.2.dist-info/licenses/LICENSE
django_hyperscript-1.5.2.dist-info/METADATA
django_hyperscript-1.5.2.dist-info/WHEEL
django_hyperscript-1.5.2.dist-info/top_level.txt
django_hyperscript-1.5.2.dist-info/RECORD
