Metadata-Version: 2.4
Name: django-hyperscript
Version: 1.5.2
Summary: Custom Django template tag for integrating hyperscript with Django templates.
Home-page: https://github.com/LucLor06/django-hyperscript
Author: Lucas Lorenz
Author-email: LukeLorenzBA@gmail.com
License: MIT
Project-URL: Documentation, https://github.com/LucLor06/django-hyperscript#readme
Project-URL: Source, https://github.com/LucLor06/django-hyperscript
Project-URL: Tracker, https://github.com/LucLor06/django-hyperscript/issues
Project-URL: Changelog, https://github.com/LucLor06/django-hyperscript/blob/main/CHANGELOG.md
Keywords: django hyperscript template-tags frontend backend-integration
Classifier: Development Status :: 5 - Production/Stable
Classifier: Framework :: Django
Classifier: Framework :: Django :: 3.2
Classifier: Framework :: Django :: 4.0
Classifier: Programming Language :: Python
Classifier: Programming Language :: Python :: 3
Classifier: Programming Language :: Python :: 3.8
Classifier: Programming Language :: Python :: 3.9
Classifier: Programming Language :: Python :: 3.10
Classifier: Programming Language :: Python :: 3.11
Classifier: License :: OSI Approved :: MIT License
Classifier: Operating System :: OS Independent
Requires-Python: >=3.6
License-File: LICENSE
Requires-Dist: Django>=3.2
Requires-Dist: hyperscript-dump>=1.0.4
Dynamic: author
Dynamic: author-email
Dynamic: classifier
Dynamic: description
Dynamic: description-content-type
Dynamic: home-page
Dynamic: keywords
Dynamic: license
Dynamic: license-file
Dynamic: project-url
Dynamic: requires-dist
Dynamic: requires-python
Dynamic: summary
